c_custom_code_checker
