Metadata-Version: 2.1
Name: c-custom-code-checker
Version: 1.0.4
Summary: Syntax checker with custom rules for c language. Create rules with your team and consider using this tool to help verify the projects developed
Author-email: Yago Caetano <yago_caetano@outlook.com>
Project-URL: Homepage, https://github.com/Yago-Caetano/c-custom-code-checker
Classifier: Programming Language :: Python :: 3
Classifier: Operating System :: OS Independent
Requires-Python: >=3.9
